<?xml version="1.0" encoding="UTF-8"?>
<MetaDataObject xmlns="http://v8.1c.ru/8.3/MDClasses" xmlns:app="http://v8.1c.ru/8.2/managed-application/core" xmlns:cfg="http://v8.1c.ru/8.1/data/enterprise/current-config" xmlns:cmi="http://v8.1c.ru/8.2/managed-application/cmi" xmlns:ent="http://v8.1c.ru/8.1/data/enterprise" xmlns:lf="http://v8.1c.ru/8.2/managed-application/logform" xmlns:style="http://v8.1c.ru/8.1/data/ui/style" xmlns:sys="http://v8.1c.ru/8.1/data/ui/fonts/system" xmlns:v8="http://v8.1c.ru/8.1/data/core" xmlns:v8ui="http://v8.1c.ru/8.1/data/ui" xmlns:web="http://v8.1c.ru/8.1/data/ui/colors/web" xmlns:win="http://v8.1c.ru/8.1/data/ui/colors/windows" xmlns:xen="http://v8.1c.ru/8.3/xcf/enums" xmlns:xpr="http://v8.1c.ru/8.3/xcf/predef" xmlns:xr="http://v8.1c.ru/8.3/xcf/readable" xmlns:xs="http://www.w3.org/2001/XMLSchema" xmlns:xsi="http://www.w3.org/2001/XMLSchema-instance" version="2.17">
	<HTTPService uuid="824406f6-43a9-4e3e-960e-39a9eed432cb">
		<Properties>
			<Name>mcp_APIBackend</Name>
			<Synonym>
				<v8:item>
					<v8:lang>ru</v8:lang>
					<v8:content>Бэкэнд API для MCP</v8:content>
				</v8:item>
			</Synonym>
			<Comment/>
			<RootURL>mcp</RootURL>
			<ReuseSessions>AutoUse</ReuseSessions>
			<SessionMaxAge>20</SessionMaxAge>
		</Properties>
		<ChildObjects>
			<URLTemplate uuid="a669bf45-5a33-4e83-9605-448e3d5029ce">
				<Properties>
					<Name>rpc</Name>
					<Synonym>
						<v8:item>
							<v8:lang>ru</v8:lang>
							<v8:content>Rpc</v8:content>
						</v8:item>
					</Synonym>
					<Comment/>
					<Template>/rpc</Template>
				</Properties>
				<ChildObjects>
					<Method uuid="71b655cd-93b3-427f-b531-709972c02d89">
						<Properties>
							<Name>POST</Name>
							<Synonym>
								<v8:item>
									<v8:lang>ru</v8:lang>
									<v8:content>POST</v8:content>
								</v8:item>
							</Synonym>
							<Comment/>
							<HTTPMethod>POST</HTTPMethod>
							<Handler>rpcPOST</Handler>
						</Properties>
					</Method>
				</ChildObjects>
			</URLTemplate>
			<URLTemplate uuid="0f0973cc-bed9-4494-a3d6-274d79a3a5c9">
				<Properties>
					<Name>health</Name>
					<Synonym>
						<v8:item>
							<v8:lang>ru</v8:lang>
							<v8:content>Health</v8:content>
						</v8:item>
					</Synonym>
					<Comment/>
					<Template>/health</Template>
				</Properties>
				<ChildObjects>
					<Method uuid="e96ab3b0-15e1-4e28-b73f-7c853a4ebfe1">
						<Properties>
							<Name>GET</Name>
							<Synonym>
								<v8:item>
									<v8:lang>ru</v8:lang>
									<v8:content>GET</v8:content>
								</v8:item>
							</Synonym>
							<Comment/>
							<HTTPMethod>GET</HTTPMethod>
							<Handler>healthGET</Handler>
						</Properties>
					</Method>
				</ChildObjects>
			</URLTemplate>
			<URLTemplate uuid="9292073a-3405-4d4f-ba9a-90a8d054f3ff">
				<Properties>
					<Name>mcp</Name>
					<Synonym>
						<v8:item>
							<v8:lang>ru1</v8:lang>
							<v8:content>Mcp</v8:content>
						</v8:item>
					</Synonym>
					<Comment/>
					<Template>/*</Template>
				</Properties>
				<ChildObjects>
					<Method uuid="c6094c73-651e-4f90-9e4d-3ed3adbb4885">
						<Properties>
							<Name>POST</Name>
							<Synonym>
								<v8:item>
									<v8:lang>ru1</v8:lang>
									<v8:content>POST</v8:content>
								</v8:item>
							</Synonym>
							<Comment/>
							<HTTPMethod>POST</HTTPMethod>
							<Handler>mcpPOST</Handler>
						</Properties>
					</Method>
					<Method uuid="c9658ca3-90ac-43fa-9387-36a9b092b531">
						<Properties>
							<Name>GET</Name>
							<Synonym>
								<v8:item>
									<v8:lang>ru1</v8:lang>
									<v8:content>GET</v8:content>
								</v8:item>
							</Synonym>
							<Comment/>
							<HTTPMethod>GET</HTTPMethod>
							<Handler>mcpGET</Handler>
						</Properties>
					</Method>
				</ChildObjects>
			</URLTemplate>
		</ChildObjects>
	</HTTPService>
</MetaDataObject>